[
    {"id" : 1,"nombre": "calza negra", "precio":1000 , "img":"/calzas/calza-negra.jpg","cantidad": 1}, 
    {"id" : 2,"nombre": "calza negra nike", "precio":2500, "img":"/calzas/LO_NIFW21085-1.jpg","cantidad": 1},
    {"id" : 3,"nombre": "calza adidad blanca", "precio":3000, "img":"/calzas/LO_NIFW21085-1.jpg", "cantidad": 1},
    {"id" : 4,"nombre": "campera deportiva","precio":4000,"img":"/calzas/NI_CU5293-010-1.jpg","cantidad": 1},
    {"id" : 5,"nombre": "campera deportiva adidas","precio":3000,"img":"/calzas/NI_DD5153-010-1.jpg","cantidad": 1},
    {"id" : 6,"nombre": "campera deportiva camuflada","precio":3000,"img":"/calzas/PU_521065-02-1.jpg ", "cantidad": 1},
    {"id" : 7,"nombre": "remera","precio":3000,"img":"/hombre/h_n_buzo1.png", "cantidad": 1},
    {"id" : 8,"nombre": "remera termica","precio":2000,"img":"/hombre/h_n_buzo2.png", "cantidad": 1},
    {"id" : 9,"nombre": "buzo mujer","precio": 2000,"img":"/mujer/m_r_buzo2.png", "cantidad": 1},
    {"id" : 10,"nombre": "buzo naranja","precio": 2000,"img":"/mujer/m_r_buzo3.png", "cantidad": 1},
    {"id" : 11,"nombre": "buzo termico","precio": 2000,"img":"/mujer/m_R_buzo1.png", "cantidad": 1},
    {"id" : 12,"nombre": "campera mujer","precio":2000,"img":"/mujer/m_n_buzo1.png", "cantidad": 1}

]

